invenio_base/__init__.py
invenio_base/__main__.py
invenio_base/app.py
invenio_base/cli.py
invenio_base/jws.py
invenio_base/signals.py
invenio_base/utils.py
invenio_base/wsgi.py
invenio_base/urls/__init__.py
invenio_base/urls/builders.py
invenio_base/urls/helpers.py
invenio_base/urls/proxies.py
invenio_base-2.3.2.dist-info/licenses/AUTHORS.rst
invenio_base-2.3.2.dist-info/licenses/LICENSE
invenio_base-2.3.2.dist-info/METADATA
invenio_base-2.3.2.dist-info/WHEEL
invenio_base-2.3.2.dist-info/entry_points.txt
invenio_base-2.3.2.dist-info/top_level.txt
invenio_base-2.3.2.dist-info/RECORD
