Metadata-Version: 2.4
Name: invenio-base
Version: 2.3.2
Summary: "Base package for building Invenio application factories."
Home-page: https://github.com/inveniosoftware/invenio-base
Author: CERN
Author-email: info@inveniosoftware.org
License: MIT
Keywords: invenio
Platform: any
Classifier: Development Status :: 5 - Production/Stable
Requires-Python: >=3.7
License-File: LICENSE
License-File: AUTHORS.rst
Requires-Dist: blinker>=1.4
Requires-Dist: Flask>=3.0.0
Requires-Dist: itsdangerous>=2.1.0
Requires-Dist: MarkupSafe>=0.23
Requires-Dist: Werkzeug>=3.0.0
Requires-Dist: watchdog>2.0.0
Requires-Dist: importlib-metadata>=4.4
Requires-Dist: importlib-resources>=5.0
Provides-Extra: tests
Requires-Dist: freezegun>=1.5.1; extra == "tests"
Requires-Dist: pytest-black-ng>=0.4.0; extra == "tests"
Requires-Dist: pytest-invenio>=1.4.2; extra == "tests"
Requires-Dist: sphinx>=4.2.0; extra == "tests"
Dynamic: license-file
